{
  "header":{
    "current_page": "save_and_multiply",
    "current_language": "ru",
    "phoneNumber": "+7 (495) 662 76 77",
    "phoneLink": "tel:+7-495-662-7677",
    "type": "addLinksButton",

    "langs":{
      "default": "ru",
      "list_2": [
        {"lang":"ru"},
        {"lang":"en"},
        {"lang":"de"}
      ],
      "list": {
        "ru":"ru",
        "en":"en",
        "de":"de"
      }
    }

  },

  "menu": {
    "list":[
      {
        "page": "save_and_multiply",
        "text":{
          "ru": "Сохранить и приумножить",
          "en": "Save and multiply",
          "de": "Speichern und wachsen"
        }
      },
      {

        "page": "get_founding",
        "text":{
          "ru": "Получить финансирование",
          "en": "Get founding",
          "de": "Bekommen Finanzierung"
        }
      },
      {

        "page": "business_solutions",
        "text":{
          "ru": "Решение для вашего бизнеса",
          "en": "Business solutions",
          "de": "Die Lösung für Ihr Geschäft"
        }
      },
      {
        "page": "banking_services",
        "text":{
          "ru": "Банковское обслуживание",
          "en": "Banking services",
          "de": "Bankdienstleistungen"
        }
      },
      {
        "page": "family_solutions",
        "text":{
          "ru": "Решения для вашей семьи и консалтинг",
          "en": "Family solutions",
          "de": "Lösungen für Ihre Familie und Beratung"
        }
      },
      {
        "type": "separator"
      },
      {
        "page": "about",
        "text":{
          "ru": "О нас",
          "en": "About us",
          "de": "Über uns"
        }
      },
      {
        "page": "contacts",
        "text":{
          "ru": "Контактная информация",
          "en": "Contacts",
          "de": "Kontaktinformationen"
        }
      }
    ],
    "buttons":[
      {
        "text":"Raiffeisen-Online",
        "href": "https://online.raiffeisen.ru/",
        "class": "button_dark"
      },
      {
        "text":"R-Dealer",
        "href": "r-dealer.html",
        "class": "button_small"
      }
    ]
    
  },

  "content": {  
      "save_and_multiply": {
        "image": "1",
        "title": {
          "ru": "Сохранить и приумножить",
          "en": "Save and multiply",
          "de": "Speichern und wachsen"
        },
        "text": {
          "ru":[
            "<p>Московский офис Friedrich Wilhelm Raiffeisen предлагает</p><p> Широкий выбор кредитных продуктов в России — кредит на покупку жилой недвижимости;</p><p> кредит под залог недвижимости — как жилой, так и коммерческой; потребительный беззалоговый кредит;</p><p> кредит, обеспеченный залогом собственного векселя Банка</p><p> Выпуск банковских гарантий с целью обеспечения обязательств перед третьими сторонами — гарантия платежа, гарантия возврата аванса и другие виды гарантий.</p>"              
          ],
          "en":[
            "<p> The Moscow office of Friedrich Wilhelm Raiffeisen offers</p><p> a wide range of loan products in Russia - a loan for the purchase of residential real estate;</p><p> a loan secured by real estate - both residential and commercial; consumer unsecured loan;</p><p> loan secured by the Bank’s own promissory note</p><p> Issuance of bank guarantees to secure liabilities to third parties - a guarantee of payment, an advance guarantee guarantee and other types of guarantees.</p> "
           ],
          "de":[
            "<p> Das Moskauer Büro von Friedrich Wilhelm Raiffeisen bietet eine breite Palette von Kreditprodukten in Russland - ein Darlehen für den Kauf von Wohnimmobilien;</p><p> ein Darlehen durch Immobilien gesichert - sowohl Wohnen und Gewerbe, Verbraucher unbesichertes Darlehen;</p><p> durch eigenes Schuldscheindarlehen gesicherter Kredit</p><p> Ausgabe von Bankbürgschaften zur Besicherung von Verbindlichkeiten gegenüber Dritten - eine Zahlungsgarantie, eine Garantievorauszahlung und andere Arten von Garantien.</p> "          ]
        }
      },
      "get_founding": {
        "image":"2",
        "title":{
            "ru": "Получить финансирование",
            "en": "Get founding",
            "de": "Bekommen Finanzierung"
          },
        "text":{
          "ru":[
            "<p>Московский офис Friedrich Wilhelm Raiffeisen предлагает </p><p>Широкий выбор кредитных продуктов в России — кредит на покупку жилой недвижимости;</p><p>кредит под залог недвижимости — как жилой, так и коммерческой; потребительный беззалоговый кредит;</p><p> кредит, обеспеченный залогом собственного векселя Банка</p><p> Выпуск банковских гарантий с целью обеспечения обязательств перед третьими сторонами — гарантия платежа, гарантия возврата аванса и другие виды гарантий.</p>"              
          ],
          "en":[
            "<p>The Moscow office of Friedrich Wilhelm Raiffeisen offers</p><p>a wide range of loan products in Russia - a loan for the purchase of residential real estate;</p><p>a loan secured by real estate - both residential and commercial; consumer unsecured loan;</p><p> loan secured by the Bank’s own promissory note</p><p> Issuance of bank guarantees to secure liabilities to third parties - a guarantee of payment, an advance guarantee guarantee and other types of guarantees.</p> "
          ],
          "de":[
            "<p>Das Moskauer Büro von Friedrich Wilhelm Raiffeisen bietet eine breite Palette von Kreditprodukten in Russland - ein Darlehen für den Kauf von Wohnimmobilien;</p><p>ein Darlehen durch Immobilien gesichert - sowohl Wohnen und Gewerbe, Verbraucher unbesichertes Darlehen;</p><p> durch eigenes Schuldscheindarlehen gesicherter Kredit</p><p> Ausgabe von Bankbürgschaften zur Besicherung von Verbindlichkeiten gegenüber Dritten - eine Zahlungsgarantie, eine Garantievorauszahlung und andere Arten von Garantien.</p> "
          ]
        }
      },
      "business_solutions": {
        "image":"3",
        "title": {
            "ru": "Решение для вашего бизнеса",
            "en": "Business solutions",
            "de": "Die Lösung für Ihr Geschäft"
          },
        "text": {
          "ru":[
             "<p>Сделки на рынках акционерного и долгового капитала <div class='inner-part__text'><span class='inner-part__line'></span> поиск инвесторов</div><div class='inner-part__text'><span class='inner-part__line'></span> поиск объектов / бизнеса для приобретения</div><div class='inner-part__text'><span class='inner-part__line'></span> оценка стоимости бизнеса</div><div class='inner-part__text'><span class='inner-part__line'></span> комплексное сопровождение и структурирование сделок</div><div class='inner-part__text'><span class='inner-part__line'></span> привлечение инвестиций на рынке капитала — IPO, SPO, private placements</div></p><p> Налоговое планирование и юридическое сопровождение корпоративных и личных активов в России и за рубежом</p>"               
            ],
          "en":[
           "<p>Equity and debt capital markets <div class='inner-part__text'><span class='inner-part__line'></span> investor search</div><div class='inner-part__text'><span class='inner-part__line'></span> search for objects / business to be acquired </div><div class='inner-part__text'><span class='inner-part__line'></span> rating business value </div><div class='inner-part__text'><span class='inner-part__line'></span> comprehensive support and structuring of transactions </div><div class='inner-part__text'><span class='inner-part__line'></span> attraction of investments in the capital market - IPO, SPO, private placements </div></p><p> Tax planning and legal support of corporate and personal assets in Russia and abroad</p> "
          ],
          "de":[
            "<p>Eigenkapital- und Fremdkapitalmärkte <div class='inner-part__text'><span class='inner-part__line'></span> Investorensuche </div><div class='inner-part__text'><span class='inner-part__line'></span> suche nach zu erfassenden Objekten / Unternehmen </div><div class='inner-part__text'><span class='inner-part__line'></span> Bewertung Geschäftswert </div><div class='inner-part__text'><span class='inner-part__line'></span> umfassende Unterstützung und Strukturierung von Transaktionen </div><div class='inner-part__text'><span class='inner-part__line'></span> Attraktivität von Investitionen am Kapitalmarkt - IPO, SPO, Privatplatzierungen </div></p><p> Steuerplanung und rechtliche Begleitung von Firmen- und Privatvermögen in Russland und im Ausland</p> "
          ]
        }
      },
      "banking_services": {
        "image":"4",
        "title": {
          "ru": "Банковское обслуживание",
          "en": "Banking services",
          "de": "Bankdienstleistungen"
        },
        "text":{
          "ru":[
             "<div class='inner-part__text'><span class='inner-part__line'></span> Дистанционное обслуживание счетов</div><div class='inner-part__text'><span class='inner-part__line'></span> Специальный курс конвертации валют, в том числе в режиме онлайн в системах R-Online, R-Dealer</div><div class='inner-part__text'><span class='inner-part__line'></span>  Широкий выбор премиальных дебетовых и кредитных карт Visa и МasterCard</div><div class='inner-part__text'><span class='inner-part__line'></span>  Расчеты через аккредитивы</div><div class='inner-part__text'><span class='inner-part__line'></span>  Счета в одиннадцати валютах: рублях, долларах США, евро, швейцарских франках, фунтах стерлингов, японских йенах, норвежских кронах, шведских кронах, австралийских долларах, канадских долларах, китайских юанях</div></p>"           
          ],
          "en":[
            "<div class='inner-part__text'><span class='inner-part__line'></span> Remote account maintenance </div><div class='inner-part__text'><span class='inner-part__line'></span> Special currency exchange rate, including online mode in R-Online systems, R-Dealer</div><div class='inner-part__text'><span class='inner-part__line '></span> A wide selection of premium debit and credit cards Visa and MasterCard </div><div class='inner-part__text'><span class='inner-part__line'></span> Payments through letters of credit </div> <div class='inner-part__text'><span class='inner-part__line'></span> Accounts in eleven currencies: rubles, US dollars, euros, Swiss francs, pounds sterling, Japanese yens, Norwegian kr onah, Swedish kronah, Australian dollars, Canadian dollars, Chinese yuan </div></p> "
            ],
          "de":[
            "<div class='inner-part__text'><span class='inner-part__line'></span> Remote-Kontoverwaltung </div><div class='inner-part__text'><span class='inner-part__line'></span> Spezieller Wechselkurs, einschließlich Online-Modus in R-Online-Systemen, R-Dealer</div><div class='inner-part__text'><span class='inner-part__line'></span> Eine große Auswahl an Premium-Debit- und Kreditkarten Visa und MasterCard </div><div class='inner-part__text'><span class='inner-part__line'></span> Zahlungen durch Akkreditive </div><div class='inner-part__text'><span class='inner-part__line'></span> Konten in elf Währungen: Rubel, US-Dollar, Euro, Schweizer Franken, Pfund Sterling, Japanische Yen, Norwegische Kronen Onah, Schwedische Krone, Australische Dollar, Kanadische Dollar, Chinesischer Yuan</div></p> "
          ]
        }
      },
      "family_solutions": {
        "image":"5",
        "title": {
          "ru": "Решения для вашей семьи и консалтинг",
          "en": "Family solutions",
          "de": "Lösungen für Ihre Familie und Beratung"
        },
        "text": {
          "ru":[
            "<div class='inner-part__text'><span class='inner-part__line'></span>  Услуги профессиональных посредников для решения задач по структурированию владения активами и вопросам наследования </div><div class='inner-part__text'><span class='inner-part__line'></span>  Налоговое планирование и юридическое сопровождение личных активов в России и за рубежом </div><div class='inner-part__text'><span class='inner-part__line'></span>  Комплексные решения по приобретению и финансированию крупных активов: коммерческая и жилая недвижимость в России и за рубежом, самолеты, яхты </div><div class='inner-part__text'><span class='inner-part__line'></span>  Финансовая защита благосостояния семьи — индивидуальные программы страхования жизни </div><div class='inner-part__text'><span class='inner-part__line'></span>  Поддержка в решении индивидуальных запросов вашей семьи </div><div class='inner-part__text'><span class='inner-part__line'></span>  Участие в наиболее ярких событиях культурной жизни Москвы</div></p>"
          ],
          "en":[
            "<div class='inner-part__text'><span class='inner-part__line'></span> Professional intermediary services for solving problems of structuring asset ownership and inheritance issues </div><div class='inner-part__text '><span class='inner-part__line'></span> Tax planning and legal support of personal assets in Russia and abroad </div><div class='inner-part__text'><span class='inner-part__line'></span> Complex solutions for the acquisition and financing of large assets: commercial and residential real estate in Russia and abroad, airplanes, yachts </div><div class='inner-part__text'><span class='inner-part__line'></span> Financial Welfare Protection Family Family - Individual Life Insurance Programs </div><div class='inner-part__text'><span class='inner-part__line'></span> Support in solving individual requests of your family </div><div class='inner-part__text'><span class='inner-part__line'></span> Participation in the most significant events in the cultural life of Moscow </div></p> "
          ],
          "de":[
            "<div class='inner-part__text'><span class='inner-part__line'></span> Professionelle Vermittlerdienste zur Lösung von Problemen bei der Strukturierung von Besitz- und Vererbungsproblemen von Ressourcen </div><div class='inner-part__text ><span class='inner-part__line'></span> Steuerplanung und rechtliche Unterstützung von persönlichen Vermögenswerten in Russland und im Ausland </div><div class='inner-part__text'><span class='inner-part__line'></span> Komplexe Lösungen für den Erwerb und die Finanzierung von großen Vermögenswerten: Geschäfts - und Wohnimmobilien in Russland und im Ausland, Flugzeuge, Yachten </div><div class='inner-part__text'><span class ='inner-part__line'></span> finanzieller Wohlfahrtsschutz Family Family - Individuelle Lebensversicherungsprogramme </div><div class='inner-part__text'><span class='inner-part__line'></span> Unterstützung bei der Lösung individueller Anfragen Ihrer Familie </div><div class='inner-part__text'><span class='inner-part__line'></span> Teilnahme an den bedeutendsten Ereignissen im kulturellen Leben Moskaus </div></p> "
          ]
        }
      },
      "about": {
        "image":"2",
        "title": {
          "ru": "О нас",
          "en": "About us",
          "de": "Über uns"
        },
        "text": {
          "ru":[
            "<p>Friedrich Wilhelm Raiffeisen — подразделение по работе с состоятельными клиентами АО «Райффайзенбанк», предоставляющее финансовые решения для владельцев крупного частного капитала и их семей в России и за рубежом.  <p></p> Наше главное преимущество — успешное развитие группы Райффайзен в России с 1996 года и более чем 130 - летняя история банка в Европе.</p>"
          ],
          "en":[
            "<p> Friedrich Wilhelm Raiffeisen is a division for working with wealthy clients of AO Raiffeisenbank, providing financial solutions for large private capital owners and their families in Russia and abroad. <p></p> Our main advantage is the successful development of the group Raiffeisen in Russia since 1996 and more than 130 years history of a bank in Europe.</P> "
          ],
          "de":[
            "<p> Friedrich Wilhelm Raiffeisen ist eine Abteilung für die Zusammenarbeit mit vermögenden Kunden der AO Raiffeisenbank und bietet Finanzlösungen für große private Kapitaleigner und deren Familien in Russland und im Ausland. <p></p> Unser Hauptvorteil ist die erfolgreiche Entwicklung der Gruppe Raiffeisen in Russland seit 1996 und mehr als 130 Jahre Bankgeschichte in Europa.</P> "
          ]
        }
      },
      "contacts": {
        "image":"1",
        "title": {
          "ru": "Контактная информация",
          "en": "Contacts",
          "de": "Kontaktinformationen"
        },
        "text": {
          "ru":["Москва <br> Смоленская-Сенная площадь, д. 28, 119002 <br> E-mail: <br> PrivateBanking@raiffeisen.ru <br> <br> Санкт-Петербург <br> Набережная реки Мойки, д. 36, 191186 <br> E-mail: <br> PrivateBanking@raiffeisen.ru <br> <br> Служба поддержки клиентов Private Line <br> Тел.: <br> +7 (495) 662 76 77 <br> 8 (800) 700 76 77 <br> Факс: <br> +7 (495) 662 76 77 <br> E-mail: <br> Private_Line@raiffeisen.ru"       
          ],
          "en":[
            "Moscow, Smolenskaya-Sennaya square, 28, 119002 E-mail: PrivateBanking@raiffeisen.ru Moscow, Saint Petersburg, The embankment of the river Moika, 36, 191186 <br> E-mail: <br> PrivateBanking@raiffeisen.ru <br> <br> Customer Support Service Private Line <br> Tel .: +7 (495) 662 76 77 <br> 8 (800 ) 700 76 77 <br> Fax: Phone: +7 (495) 662 76 77 <br> E-mail: Private_Line@raiffeisen.ru "
          ],
          "de":[
            "Moskau, Smolenskaja-Sennaja-Platz, 28, 119002 E-Mail: PrivateBanking@raiffeisen.ru Moskau, Sankt Petersburg, Die Böschung der Moika, 36, 191186 <br> E-mail: <br> PrivatBanking@raiffeisen.ru <br> <br> Kundenservice Privatleitung <br> Tel.: +7 (495) 662 76 77 <br> 8 (800 ) 700 76 77 <br> Fax: Telefon: +7 (495) 662 76 77 E-mail: Private_Line@raiffeisen.ru "
          ]
        }
      }
  },

  "content_2": {
      "save_and_multiply": {
        "image":"1",
        "title":"Сохранить и приумножить",
        "text":[
            "<p>Обслуживание в московском офисе Friedrich Wilhelm Raiffeisen сочетает в себе преимущества индивидуального клиентского сервиса в Москве с инвестиционными решениями, разработанными в центральном офисе Группы Райффайзен в Вене. </p><p> Каждый клиент российского офиса Friedrich Wilhelm Raiffeisen получает персонального менеджера в Москве, который осуществляет открытие и обслуживание инвестиционных счетов в Австрии, а также обеспечивает доступ к международному рынку ценных бумаг через платформы в России и за рубежом. </p><p> Специалисты Friedrich Wilhelm Raiffeisen в Австрии разрабатывают индивидуальные стратегии доверительного управления активами и осуществляют формирование индивидуального портфеля, отвечающего инвестиционным потребностям клиента. </p><p> Friedrich Wilhelm Raiffeisen оказывает брокерские, консультационные и аналитические услуги, предоставляет гибкие депозитные предложения и обслуживает счета в 11 валютах. </p><p> Узнать об инвестиционных решениях Friedrich Wilhelm Raiffeisen <a href='#' class='inner-part__link'> в Вене</a></p>"
          ]
      },
      "get_founding": {
        "image":"2",
        "title":"Получить финансирование",
        "text":[
            "<p>Московский офис Friedrich Wilhelm Raiffeisen предлагает</p><p> Широкий выбор кредитных продуктов в России — кредит на покупку жилой недвижимости;</p><p> кредит под залог недвижимости — как жилой, так и коммерческой; потребительный беззалоговый кредит;</p><p> кредит, обеспеченный залогом собственного векселя Банка</p><p> Выпуск банковских гарантий с целью обеспечения обязательств перед третьими сторонами — гарантия платежа, гарантия возврата аванса и другие виды гарантий.</p>"              
          ]
      },
      "business_solutions": {
        "image":"3",
        "title": "Решение для вашего бизнеса",
        "text":[
            "<p>Сделки на рынках акционерного и долгового капитала <div class='inner-part__text'><span class='inner-part__line'></span> поиск инвесторов</div><div class='inner-part__text'><span class='inner-part__line'></span> поиск объектов / бизнеса для приобретения</div><div class='inner-part__text'><span class='inner-part__line'></span> оценка стоимости бизнеса</div><div class='inner-part__text'><span class='inner-part__line'></span> комплексное сопровождение и структурирование сделок</div><div class='inner-part__text'><span class='inner-part__line'></span> привлечение инвестиций на рынке капитала — IPO, SPO, private placements</div></p><p> Налоговое планирование и юридическое сопровождение корпоративных и личных активов в России и за рубежом</p>"         
            ]
      },
      "banking_services": {
        "image":"4",
        "title":"Банковское обслуживание",
        "text":[
          "<div class='inner-part__text'><span class='inner-part__line'></span> Дистанционное обслуживание счетов</div><div class='inner-part__text'><span class='inner-part__line'></span> Специальный курс конвертации валют, в том числе в режиме онлайн в системах R-Online, R-Dealer</div><div class='inner-part__text'><span class='inner-part__line'></span>  Широкий выбор премиальных дебетовых и кредитных карт Visa и МasterCard</div><div class='inner-part__text'><span class='inner-part__line'></span>  Расчеты через аккредитивы</div><div class='inner-part__text'><span class='inner-part__line'></span>  Счета в одиннадцати валютах: рублях, долларах США, евро, швейцарских франках, фунтах стерлингов, японских йенах, норвежских кронах, шведских кронах, австралийских долларах, канадских долларах, китайских юанях</div></p>"           
          ]
      },
      "family_solutions": {
        "image":"5",
        "title": "Решения для вашей семьи и консалтинг",
        "text": [
          "<div class='inner-part__text'><span class='inner-part__line'></span>  Услуги профессиональных посредников для решения задач по структурированию владения активами и вопросам наследования </div><div class='inner-part__text'><span class='inner-part__line'></span>  Налоговое планирование и юридическое сопровождение личных активов в России и за рубежом </div><div class='inner-part__text'><span class='inner-part__line'></span>  Комплексные решения по приобретению и финансированию крупных активов: коммерческая и жилая недвижимость в России и за рубежом, самолеты, яхты </div><div class='inner-part__text'><span class='inner-part__line'></span>  Финансовая защита благосостояния семьи — индивидуальные программы страхования жизни </div><div class='inner-part__text'><span class='inner-part__line'></span>  Поддержка в решении индивидуальных запросов вашей семьи </div><div class='inner-part__text'><span class='inner-part__line'></span>  Участие в наиболее ярких событиях культурной жизни Москвы</div></p>"
          ]
      },
      "about": {
        "image":"2",
        "title":"О нас",
        "text":[
            "<p>Friedrich Wilhelm Raiffeisen — подразделение по работе с состоятельными клиентами АО «Райффайзенбанк», предоставляющее финансовые решения для владельцев крупного частного капитала и их семей в России и за рубежом.  <p></p> Наше главное преимущество — успешное развитие группы Райффайзен в России с 1996 года и более чем 130 - летняя история банка в Европе.</p>"
          ]
      },
      "contacts": {
        "image":"1",
        "title":"Контактная информация",
        "text": ["Москва <br> Смоленская-Сенная площадь, д. 28, 119002 <br> E-mail: <br> PrivateBanking@raiffeisen.ru <br> <br> Санкт-Петербург <br> Набережная реки Мойки, д. 36, 191186 <br> E-mail: <br> PrivateBanking@raiffeisen.ru <br> <br> Служба поддержки клиентов Private Line <br> Тел.: <br> +7 (495) 662 76 77 <br> 8 (800) 700 76 77 <br> Факс: <br> +7 (495) 662 76 77 <br> E-mail: <br> Private_Line@raiffeisen.ru"       
      ]
      }
  },
  "translates": {
    "footer_fwr": { 
      "ru": "Скачать «Услуги FWR» ",
      "en": "Download «Услуги FWR» ",
      "de": "Shaise «Услуги FWR» "
    },
    "footer_copyright": { 
      "ru": "&copy;&nbsp;2009-2017&nbsp;АО &laquo;Райффайзенбанк&raquo; ",
      "en": "&copy;&nbsp;2009-2017&nbsp;АО &laquo;Raiffeisen&raquo; ",
      "de": "&copy;&nbsp;2009-2017&nbsp;АО &laquo;Raiffeisen(D)&raquo; "
    },
    "ROnline":{
      "ru": "Райффайзен-Онлайн",
      "en": "Raiffeisen-Online",
      "de": "Raiffeisen-Online(D)"
    },
    "RDealer":{
      "ru": "Р-Дилер",
      "en": "R-Dealer",
      "de": "R-Händler"
    }
  }

}